[
    {
        "pk": 1,
        "model": "labrack.chassis",
        "fields": {
            "componentType": [],
            "owners": [],
            "variantOf": []
        }
    },
    {
        "pk": 2,
        "model": "labrack.chassis",
        "fields": {
            "componentType": [],
            "owners": [],
            "variantOf": [
                1
            ]
        }
    },
    {
        "pk": 3,
        "model": "labrack.chassis",
        "fields": {
            "componentType": [],
            "owners": [],
            "variantOf": [
                1
            ]
        }
    },
    {
        "pk": 4,
        "model": "labrack.chassis",
        "fields": {
            "componentType": [],
            "owners": [],
            "variantOf": [
                1
            ]
        }
    },
    {
        "pk": 5,
        "model": "labrack.chassis",
        "fields": {
            "componentType": [],
            "owners": [],
            "variantOf": [
                4
            ]
        }
    },
    {
        "pk": 6,
        "model": "labrack.chassis",
        "fields": {
            "componentType": [],
            "owners": [],
            "variantOf": [
                4
            ]
        }
    },
    {
        "pk": 7,
        "model": "labrack.chassis",
        "fields": {
            "componentType": [],
            "owners": [],
            "variantOf": []
        }
    },
    {
        "pk": 8,
        "model": "labrack.chassis",
        "fields": {
            "componentType": [],
            "owners": [],
            "variantOf": []
        }
    },
    {
        "pk": 9,
        "model": "labrack.chassis",
        "fields": {
            "componentType": [],
            "owners": [],
            "variantOf": []
        }
    },
    {
        "pk": 10,
        "model": "labrack.chassis",
        "fields": {
            "componentType": [],
            "owners": [],
            "variantOf": []
        }
    },
    {
        "pk": 11,
        "model": "labrack.chassis",
        "fields": {
            "componentType": [],
            "owners": [],
            "variantOf": [
                10
            ]
        }
    },
    {
        "pk": 12,
        "model": "labrack.chassis",
        "fields": {
            "componentType": [],
            "owners": [],
            "variantOf": [
                10
            ]
        }
    }
]
